miniKeras/__init__.py
miniKeras/network.py
miniKeras/unit.py
miniKeras-1.0.0.dist-info/METADATA
miniKeras-1.0.0.dist-info/WHEEL
miniKeras-1.0.0.dist-info/top_level.txt
miniKeras-1.0.0.dist-info/RECORD
