Metadata-Version: 2.1
Name: miniKeras
Version: 1.0.0
Summary: This is a scalar only supported mini-version of keras
Author: Tilak raj
Author-email: tilakraj7050@gmail.com
